wasm_py_sandbox/__init__.py
wasm_py_sandbox/bindings.py
wasm_py_sandbox/py_sandbox.wasm
wasm_py_sandbox/sandbox.py
wasm_py_sandbox-0.1.1.dist-info/LICENSE
wasm_py_sandbox-0.1.1.dist-info/METADATA
wasm_py_sandbox-0.1.1.dist-info/WHEEL
wasm_py_sandbox-0.1.1.dist-info/top_level.txt
wasm_py_sandbox-0.1.1.dist-info/RECORD
