Metadata-Version: 2.1
Name: wasm-py-sandbox
Version: 0.1.1
Summary: Sandbox environment for executing Python code
Home-page: https://github.com/JSH32/PySandbox
Author: Josh Rudnik
Author-email: rudnik7000@gmail.com
License: MIT
Project-URL: Documentation, https://github.com/JSH32/PySandbox
Project-URL: Bug Reports, https://github.com/JSH32/PySandbox/issues
Project-URL: Source Code, https://github.com/JSH32/PySandbox
Keywords: python,sandbox,wasm,wasmer
Classifier: Development Status :: 3 - Alpha
Classifier: Intended Audience :: Developers
Classifier: Topic :: Software Development :: Build Tools
Classifier: Programming Language :: Python :: 3
Classifier: Programming Language :: Python :: 3.6
Classifier: Programming Language :: Python :: 3.7
Classifier: Programming Language :: Python :: 3.8
Classifier: Programming Language :: Python :: 3.9
Classifier: Programming Language :: Python :: 3 :: Only
Classifier: License :: OSI Approved :: MIT License
Classifier: Operating System :: OS Independent
Requires-Python: >=3
License-File: LICENSE
Requires-Dist: wasmer ==1.1.0
Requires-Dist: wasmer-compiler-cranelift ==1.1.0
